Metadata-Version: 1.1
Name: osticket
Version: 0.2.0
Summary: Python module for osTicket API
Home-page: https://github.com/sascocl/osticket-api-client-python
Author: Esteban De La Fuente Rubio, DeLaF
Author-email: esteban@sasco.cl
License: LGPL
Keywords: osticket
Platform: UNKNOWN
Classifier: Development Status :: 5 - Production/Stable
Classifier: Intended Audience :: Developers
Classifier: Topic :: Software Development :: Build Tools
Classifier: License :: OSI Approved :: GNU Lesser General Public License v3 or later (LGPLv3+)
Classifier: Programming Language :: Python :: 3
